MANIFEST.in
README.md
setup.py
yd/__init__.py
yd/dbcache.py
yd/environ.py
yd/version.py
yd/yd.py
yd/ydsearch.py
yd.egg-info/PKG-INFO
yd.egg-info/SOURCES.txt
yd.egg-info/dependency_links.txt
yd.egg-info/entry_points.txt
yd.egg-info/not-zip-safe
yd.egg-info/top_level.txt