Metadata-Version: 1.0
Name: yd
Version: 1.3.5
Summary: A terminal bilingual dictionary
Home-page: https://github.com/wierton/dict
Author: wierton
Author-email: nickouxianfei@gmail.com
License: UNKNOWN
Platform: UNKNOWN
